{"id":216994814,"node_id":"MDEwOlJlcG9zaXRvcnkyMTY5OTQ4MTQ=","name":"FGData","full_name":"CNFeelGood/FGData","private":false,"owner":{"login":"CNFeelGood","id":33646610,"node_id":"MDQ6VXNlcjMzNjQ2NjEw","avatar_url":"https://avatars2.githubusercontent.com/u/33646610?v=4","gravatar_id":"","url":"https://api.github.com/users/CNFeelGood","html_url":"https://github.com/CNFeelGood","followers_url":"https://api.github.com/users/CNFeelGood/followers","following_url":"https://api.github.com/users/CNFeelGood/following{/other_user}","gists_url":"https://api.github.com/users/CNFeelGood/gists{/gist_id}","starred_url":"https://api.github.com/users/CNFeelGood/starred{/owner}{/repo}","subscriptions_url":"https://api.github.com/users/CNFeelGood/subscriptions","organizations_url":"https://api.github.com/users/CNFeelGood/orgs","repos_url":"https://api.github.com/users/CNFeelGood/repos","events_url":"https://api.github.com/users/CNFeelGood/events{/privacy}","received_events_url":"https://api.github.com/users/CNFeelGood/received_events","type":"User","site_admin":false},"html_url":"https://github.com/CNFeelGood/FGData","description":"some helper for data","fork":false,"url":"https://api.github.com/repos/CNFeelGood/FGData","forks_url":"https://api.github.com/repos/CNFeelGood/FGData/forks","keys_url":"https://api.github.com/repos/CNFeelGood/FGData/keys{/key_id}","collaborators_url":"https://api.github.com/repos/CNFeelGood/FGData/collaborators{/collaborator}","teams_url":"https://api.github.com/repos/CNFeelGood/FGData/teams","hooks_url":"https://api.github.com/repos/CNFeelGood/FGData/hooks","issue_events_url":"https://api.github.com/repos/CNFeelGood/FGData/issues/events{/number}","events_url":"https://api.github.com/repos/CNFeelGood/FGData/events","assignees_url":"https://api.github.com/repos/CNFeelGood/FGData/assignees{/user}","branches_url":"https://api.github.com/repos/CNFeelGood/FGData/branches{/branch}","tags_url":"https://api.github.com/repos/CNFeelGood/FGData/tags","blobs_url":"https://api.github.com/repos/CNFeelGood/FGData/git/blobs{/sha}","git_tags_url":"https://api.github.com/repos/CNFeelGood/FGData/git/tags{/sha}","git_refs_url":"https://api.github.com/repos/CNFeelGood/FGData/git/refs{/sha}","trees_url":"https://api.github.com/repos/CNFeelGood/FGData/git/trees{/sha}","statuses_url":"https://api.github.com/repos/CNFeelGood/FGData/statuses/{sha}","languages_url":"https://api.github.com/repos/CNFeelGood/FGData/languages","stargazers_url":"https://api.github.com/repos/CNFeelGood/FGData/stargazers","contributors_url":"https://api.github.com/repos/CNFeelGood/FGData/contributors","subscribers_url":"https://api.github.com/repos/CNFeelGood/FGData/subscribers","subscription_url":"https://api.github.com/repos/CNFeelGood/FGData/subscription","commits_url":"https://api.github.com/repos/CNFeelGood/FGData/commits{/sha}","git_commits_url":"https://api.github.com/repos/CNFeelGood/FGData/git/commits{/sha}","comments_url":"https://api.github.com/repos/CNFeelGood/FGData/comments{/number}","issue_comment_url":"https://api.github.com/repos/CNFeelGood/FGData/issues/comments{/number}","contents_url":"https://api.github.com/repos/CNFeelGood/FGData/contents/{+path}","compare_url":"https://api.github.com/repos/CNFeelGood/FGData/compare/{base}...{head}","merges_url":"https://api.github.com/repos/CNFeelGood/FGData/merges","archive_url":"https://api.github.com/repos/CNFeelGood/FGData/{archive_format}{/ref}","downloads_url":"https://api.github.com/repos/CNFeelGood/FGData/downloads","issues_url":"https://api.github.com/repos/CNFeelGood/FGData/issues{/number}","pulls_url":"https://api.github.com/repos/CNFeelGood/FGData/pulls{/number}","milestones_url":"https://api.github.com/repos/CNFeelGood/FGData/milestones{/number}","notifications_url":"https://api.github.com/repos/CNFeelGood/FGData/notifications{?since,all,participating}","labels_url":"https://api.github.com/repos/CNFeelGood/FGData/labels{/name}","releases_url":"https://api.github.com/repos/CNFeelGood/FGData/releases{/id}","deployments_url":"https://api.github.com/repos/CNFeelGood/FGData/deployments","created_at":"2019-10-23T07:26:54Z","updated_at":"2019-11-17T16:55:27Z","pushed_at":"2019-11-17T16:55:25Z","git_url":"git://github.com/CNFeelGood/FGData.git","ssh_url":"git@github.com:CNFeelGood/FGData.git","clone_url":"https://github.com/CNFeelGood/FGData.git","svn_url":"https://github.com/CNFeelGood/FGData","homepage":null,"size":42,"stargazers_count":0,"watchers_count":0,"language":"Objective-C","has_issues":true,"has_projects":true,"has_downloads":true,"has_wiki":true,"has_pages":false,"forks_count":0,"mirror_url":null,"archived":false,"disabled":false,"open_issues_count":0,"license":{"key":"mit","name":"MIT License","spdx_id":"MIT","url":"https://api.github.com/licenses/mit","node_id":"MDc6TGljZW5zZTEz"},"topics":[],"forks":0,"open_issues":0,"watchers":0,"default_branch":"master","permissions":{"admin":false,"push":false,"pull":true},"temp_clone_token":"","network_count":0,"subscribers_count":1}