{"id":14128433,"node_id":"MDEwOlJlcG9zaXRvcnkxNDEyODQzMw==","name":"OpenClien","full_name":"kewlbear/OpenClien","private":false,"owner":{"login":"kewlbear","id":1168866,"node_id":"MDQ6VXNlcjExNjg4NjY=","avatar_url":"https://avatars0.githubusercontent.com/u/1168866?v=4","gravatar_id":"","url":"https://api.github.com/users/kewlbear","html_url":"https://github.com/kewlbear","followers_url":"https://api.github.com/users/kewlbear/followers","following_url":"https://api.github.com/users/kewlbear/following{/other_user}","gists_url":"https://api.github.com/users/kewlbear/gists{/gist_id}","starred_url":"https://api.github.com/users/kewlbear/starred{/owner}{/repo}","subscriptions_url":"https://api.github.com/users/kewlbear/subscriptions","organizations_url":"https://api.github.com/users/kewlbear/orgs","repos_url":"https://api.github.com/users/kewlbear/repos","events_url":"https://api.github.com/users/kewlbear/events{/privacy}","received_events_url":"https://api.github.com/users/kewlbear/received_events","type":"User","site_admin":false},"html_url":"https://github.com/kewlbear/OpenClien","description":"클리앙 (http://clien.net) 비공식 iOS 라이브러리","fork":false,"url":"https://api.github.com/repos/kewlbear/OpenClien","forks_url":"https://api.github.com/repos/kewlbear/OpenClien/forks","keys_url":"https://api.github.com/repos/kewlbear/OpenClien/keys{/key_id}","collaborators_url":"https://api.github.com/repos/kewlbear/OpenClien/collaborators{/collaborator}","teams_url":"https://api.github.com/repos/kewlbear/OpenClien/teams","hooks_url":"https://api.github.com/repos/kewlbear/OpenClien/hooks","issue_events_url":"https://api.github.com/repos/kewlbear/OpenClien/issues/events{/number}","events_url":"https://api.github.com/repos/kewlbear/OpenClien/events","assignees_url":"https://api.github.com/repos/kewlbear/OpenClien/assignees{/user}","branches_url":"https://api.github.com/repos/kewlbear/OpenClien/branches{/branch}","tags_url":"https://api.github.com/repos/kewlbear/OpenClien/tags","blobs_url":"https://api.github.com/repos/kewlbear/OpenClien/git/blobs{/sha}","git_tags_url":"https://api.github.com/repos/kewlbear/OpenClien/git/tags{/sha}","git_refs_url":"https://api.github.com/repos/kewlbear/OpenClien/git/refs{/sha}","trees_url":"https://api.github.com/repos/kewlbear/OpenClien/git/trees{/sha}","statuses_url":"https://api.github.com/repos/kewlbear/OpenClien/statuses/{sha}","languages_url":"https://api.github.com/repos/kewlbear/OpenClien/languages","stargazers_url":"https://api.github.com/repos/kewlbear/OpenClien/stargazers","contributors_url":"https://api.github.com/repos/kewlbear/OpenClien/contributors","subscribers_url":"https://api.github.com/repos/kewlbear/OpenClien/subscribers","subscription_url":"https://api.github.com/repos/kewlbear/OpenClien/subscription","commits_url":"https://api.github.com/repos/kewlbear/OpenClien/commits{/sha}","git_commits_url":"https://api.github.com/repos/kewlbear/OpenClien/git/commits{/sha}","comments_url":"https://api.github.com/repos/kewlbear/OpenClien/comments{/number}","issue_comment_url":"https://api.github.com/repos/kewlbear/OpenClien/issues/comments{/number}","contents_url":"https://api.github.com/repos/kewlbear/OpenClien/contents/{+path}","compare_url":"https://api.github.com/repos/kewlbear/OpenClien/compare/{base}...{head}","merges_url":"https://api.github.com/repos/kewlbear/OpenClien/merges","archive_url":"https://api.github.com/repos/kewlbear/OpenClien/{archive_format}{/ref}","downloads_url":"https://api.github.com/repos/kewlbear/OpenClien/downloads","issues_url":"https://api.github.com/repos/kewlbear/OpenClien/issues{/number}","pulls_url":"https://api.github.com/repos/kewlbear/OpenClien/pulls{/number}","milestones_url":"https://api.github.com/repos/kewlbear/OpenClien/milestones{/number}","notifications_url":"https://api.github.com/repos/kewlbear/OpenClien/notifications{?since,all,participating}","labels_url":"https://api.github.com/repos/kewlbear/OpenClien/labels{/name}","releases_url":"https://api.github.com/repos/kewlbear/OpenClien/releases{/id}","deployments_url":"https://api.github.com/repos/kewlbear/OpenClien/deployments","created_at":"2013-11-05T01:05:43Z","updated_at":"2019-08-11T12:54:04Z","pushed_at":"2015-10-16T09:19:30Z","git_url":"git://github.com/kewlbear/OpenClien.git","ssh_url":"git@github.com:kewlbear/OpenClien.git","clone_url":"https://github.com/kewlbear/OpenClien.git","svn_url":"https://github.com/kewlbear/OpenClien","homepage":"","size":7568,"stargazers_count":29,"watchers_count":29,"language":"Objective-C","has_issues":true,"has_projects":true,"has_downloads":true,"has_wiki":true,"has_pages":true,"forks_count":9,"mirror_url":null,"archived":false,"disabled":false,"open_issues_count":0,"license":{"key":"apache-2.0","name":"Apache License 2.0","spdx_id":"Apache-2.0","url":"https://api.github.com/licenses/apache-2.0","node_id":"MDc6TGljZW5zZTI="},"topics":[],"forks":9,"open_issues":0,"watchers":29,"default_branch":"master","permissions":{"admin":false,"push":false,"pull":true},"temp_clone_token":"","network_count":9,"subscribers_count":11}