{"id":60693078,"node_id":"MDEwOlJlcG9zaXRvcnk2MDY5MzA3OA==","name":"POPButton","full_name":"OO-E/POPButton","private":false,"owner":{"login":"OO-E","id":9078907,"node_id":"MDQ6VXNlcjkwNzg5MDc=","avatar_url":"https://avatars1.githubusercontent.com/u/9078907?v=4","gravatar_id":"","url":"https://api.github.com/users/OO-E","html_url":"https://github.com/OO-E","followers_url":"https://api.github.com/users/OO-E/followers","following_url":"https://api.github.com/users/OO-E/following{/other_user}","gists_url":"https://api.github.com/users/OO-E/gists{/gist_id}","starred_url":"https://api.github.com/users/OO-E/starred{/owner}{/repo}","subscriptions_url":"https://api.github.com/users/OO-E/subscriptions","organizations_url":"https://api.github.com/users/OO-E/orgs","repos_url":"https://api.github.com/users/OO-E/repos","events_url":"https://api.github.com/users/OO-E/events{/privacy}","received_events_url":"https://api.github.com/users/OO-E/received_events","type":"User","site_admin":false},"html_url":"https://github.com/OO-E/POPButton","description":"Bounce Animation Button","fork":false,"url":"https://api.github.com/repos/OO-E/POPButton","forks_url":"https://api.github.com/repos/OO-E/POPButton/forks","keys_url":"https://api.github.com/repos/OO-E/POPButton/keys{/key_id}","collaborators_url":"https://api.github.com/repos/OO-E/POPButton/collaborators{/collaborator}","teams_url":"https://api.github.com/repos/OO-E/POPButton/teams","hooks_url":"https://api.github.com/repos/OO-E/POPButton/hooks","issue_events_url":"https://api.github.com/repos/OO-E/POPButton/issues/events{/number}","events_url":"https://api.github.com/repos/OO-E/POPButton/events","assignees_url":"https://api.github.com/repos/OO-E/POPButton/assignees{/user}","branches_url":"https://api.github.com/repos/OO-E/POPButton/branches{/branch}","tags_url":"https://api.github.com/repos/OO-E/POPButton/tags","blobs_url":"https://api.github.com/repos/OO-E/POPButton/git/blobs{/sha}","git_tags_url":"https://api.github.com/repos/OO-E/POPButton/git/tags{/sha}","git_refs_url":"https://api.github.com/repos/OO-E/POPButton/git/refs{/sha}","trees_url":"https://api.github.com/repos/OO-E/POPButton/git/trees{/sha}","statuses_url":"https://api.github.com/repos/OO-E/POPButton/statuses/{sha}","languages_url":"https://api.github.com/repos/OO-E/POPButton/languages","stargazers_url":"https://api.github.com/repos/OO-E/POPButton/stargazers","contributors_url":"https://api.github.com/repos/OO-E/POPButton/contributors","subscribers_url":"https://api.github.com/repos/OO-E/POPButton/subscribers","subscription_url":"https://api.github.com/repos/OO-E/POPButton/subscription","commits_url":"https://api.github.com/repos/OO-E/POPButton/commits{/sha}","git_commits_url":"https://api.github.com/repos/OO-E/POPButton/git/commits{/sha}","comments_url":"https://api.github.com/repos/OO-E/POPButton/comments{/number}","issue_comment_url":"https://api.github.com/repos/OO-E/POPButton/issues/comments{/number}","contents_url":"https://api.github.com/repos/OO-E/POPButton/contents/{+path}","compare_url":"https://api.github.com/repos/OO-E/POPButton/compare/{base}...{head}","merges_url":"https://api.github.com/repos/OO-E/POPButton/merges","archive_url":"https://api.github.com/repos/OO-E/POPButton/{archive_format}{/ref}","downloads_url":"https://api.github.com/repos/OO-E/POPButton/downloads","issues_url":"https://api.github.com/repos/OO-E/POPButton/issues{/number}","pulls_url":"https://api.github.com/repos/OO-E/POPButton/pulls{/number}","milestones_url":"https://api.github.com/repos/OO-E/POPButton/milestones{/number}","notifications_url":"https://api.github.com/repos/OO-E/POPButton/notifications{?since,all,participating}","labels_url":"https://api.github.com/repos/OO-E/POPButton/labels{/name}","releases_url":"https://api.github.com/repos/OO-E/POPButton/releases{/id}","deployments_url":"https://api.github.com/repos/OO-E/POPButton/deployments","created_at":"2016-06-08T11:32:16Z","updated_at":"2016-06-08T11:36:31Z","pushed_at":"2016-06-14T15:33:30Z","git_url":"git://github.com/OO-E/POPButton.git","ssh_url":"git@github.com:OO-E/POPButton.git","clone_url":"https://github.com/OO-E/POPButton.git","svn_url":"https://github.com/OO-E/POPButton","homepage":null,"size":67,"stargazers_count":0,"watchers_count":0,"language":"Swift","has_issues":true,"has_projects":true,"has_downloads":true,"has_wiki":true,"has_pages":false,"forks_count":0,"mirror_url":null,"archived":false,"disabled":false,"open_issues_count":0,"license":{"key":"mit","name":"MIT License","spdx_id":"MIT","url":"https://api.github.com/licenses/mit","node_id":"MDc6TGljZW5zZTEz"},"topics":[],"forks":0,"open_issues":0,"watchers":0,"default_branch":"master","permissions":{"admin":false,"push":false,"pull":true},"temp_clone_token":"","network_count":0,"subscribers_count":1}