{"id":157307861,"node_id":"MDEwOlJlcG9zaXRvcnkxNTczMDc4NjE=","name":"QiQRCode","full_name":"QiShare/QiQRCode","private":false,"owner":{"login":"QiShare","id":41294261,"node_id":"MDQ6VXNlcjQxMjk0MjYx","avatar_url":"https://avatars3.githubusercontent.com/u/41294261?v=4","gravatar_id":"","url":"https://api.github.com/users/QiShare","html_url":"https://github.com/QiShare","followers_url":"https://api.github.com/users/QiShare/followers","following_url":"https://api.github.com/users/QiShare/following{/other_user}","gists_url":"https://api.github.com/users/QiShare/gists{/gist_id}","starred_url":"https://api.github.com/users/QiShare/starred{/owner}{/repo}","subscriptions_url":"https://api.github.com/users/QiShare/subscriptions","organizations_url":"https://api.github.com/users/QiShare/orgs","repos_url":"https://api.github.com/users/QiShare/repos","events_url":"https://api.github.com/users/QiShare/events{/privacy}","received_events_url":"https://api.github.com/users/QiShare/received_events","type":"User","site_admin":false},"html_url":"https://github.com/QiShare/QiQRCode","description":"iOS原生扫描二维码和生成二维码","fork":false,"url":"https://api.github.com/repos/QiShare/QiQRCode","forks_url":"https://api.github.com/repos/QiShare/QiQRCode/forks","keys_url":"https://api.github.com/repos/QiShare/QiQRCode/keys{/key_id}","collaborators_url":"https://api.github.com/repos/QiShare/QiQRCode/collaborators{/collaborator}","teams_url":"https://api.github.com/repos/QiShare/QiQRCode/teams","hooks_url":"https://api.github.com/repos/QiShare/QiQRCode/hooks","issue_events_url":"https://api.github.com/repos/QiShare/QiQRCode/issues/events{/number}","events_url":"https://api.github.com/repos/QiShare/QiQRCode/events","assignees_url":"https://api.github.com/repos/QiShare/QiQRCode/assignees{/user}","branches_url":"https://api.github.com/repos/QiShare/QiQRCode/branches{/branch}","tags_url":"https://api.github.com/repos/QiShare/QiQRCode/tags","blobs_url":"https://api.github.com/repos/QiShare/QiQRCode/git/blobs{/sha}","git_tags_url":"https://api.github.com/repos/QiShare/QiQRCode/git/tags{/sha}","git_refs_url":"https://api.github.com/repos/QiShare/QiQRCode/git/refs{/sha}","trees_url":"https://api.github.com/repos/QiShare/QiQRCode/git/trees{/sha}","statuses_url":"https://api.github.com/repos/QiShare/QiQRCode/statuses/{sha}","languages_url":"https://api.github.com/repos/QiShare/QiQRCode/languages","stargazers_url":"https://api.github.com/repos/QiShare/QiQRCode/stargazers","contributors_url":"https://api.github.com/repos/QiShare/QiQRCode/contributors","subscribers_url":"https://api.github.com/repos/QiShare/QiQRCode/subscribers","subscription_url":"https://api.github.com/repos/QiShare/QiQRCode/subscription","commits_url":"https://api.github.com/repos/QiShare/QiQRCode/commits{/sha}","git_commits_url":"https://api.github.com/repos/QiShare/QiQRCode/git/commits{/sha}","comments_url":"https://api.github.com/repos/QiShare/QiQRCode/comments{/number}","issue_comment_url":"https://api.github.com/repos/QiShare/QiQRCode/issues/comments{/number}","contents_url":"https://api.github.com/repos/QiShare/QiQRCode/contents/{+path}","compare_url":"https://api.github.com/repos/QiShare/QiQRCode/compare/{base}...{head}","merges_url":"https://api.github.com/repos/QiShare/QiQRCode/merges","archive_url":"https://api.github.com/repos/QiShare/QiQRCode/{archive_format}{/ref}","downloads_url":"https://api.github.com/repos/QiShare/QiQRCode/downloads","issues_url":"https://api.github.com/repos/QiShare/QiQRCode/issues{/number}","pulls_url":"https://api.github.com/repos/QiShare/QiQRCode/pulls{/number}","milestones_url":"https://api.github.com/repos/QiShare/QiQRCode/milestones{/number}","notifications_url":"https://api.github.com/repos/QiShare/QiQRCode/notifications{?since,all,participating}","labels_url":"https://api.github.com/repos/QiShare/QiQRCode/labels{/name}","releases_url":"https://api.github.com/repos/QiShare/QiQRCode/releases{/id}","deployments_url":"https://api.github.com/repos/QiShare/QiQRCode/deployments","created_at":"2018-11-13T02:26:23Z","updated_at":"2019-12-18T11:55:12Z","pushed_at":"2019-01-31T04:07:06Z","git_url":"git://github.com/QiShare/QiQRCode.git","ssh_url":"git@github.com:QiShare/QiQRCode.git","clone_url":"https://github.com/QiShare/QiQRCode.git","svn_url":"https://github.com/QiShare/QiQRCode","homepage":null,"size":162,"stargazers_count":41,"watchers_count":41,"language":"Objective-C","has_issues":true,"has_projects":true,"has_downloads":true,"has_wiki":true,"has_pages":false,"forks_count":7,"mirror_url":null,"archived":false,"disabled":false,"open_issues_count":3,"license":{"key":"mit","name":"MIT License","spdx_id":"MIT","url":"https://api.github.com/licenses/mit","node_id":"MDc6TGljZW5zZTEz"},"topics":[],"forks":7,"open_issues":3,"watchers":41,"default_branch":"master","permissions":{"admin":false,"push":false,"pull":true},"temp_clone_token":"","network_count":7,"subscribers_count":0}