{"id":181677559,"node_id":"MDEwOlJlcG9zaXRvcnkxODE2Nzc1NTk=","name":"Sourceful","full_name":"twostraws/Sourceful","private":false,"owner":{"login":"twostraws","id":190200,"node_id":"MDQ6VXNlcjE5MDIwMA==","avatar_url":"https://avatars3.githubusercontent.com/u/190200?v=4","gravatar_id":"","url":"https://api.github.com/users/twostraws","html_url":"https://github.com/twostraws","followers_url":"https://api.github.com/users/twostraws/followers","following_url":"https://api.github.com/users/twostraws/following{/other_user}","gists_url":"https://api.github.com/users/twostraws/gists{/gist_id}","starred_url":"https://api.github.com/users/twostraws/starred{/owner}{/repo}","subscriptions_url":"https://api.github.com/users/twostraws/subscriptions","organizations_url":"https://api.github.com/users/twostraws/orgs","repos_url":"https://api.github.com/users/twostraws/repos","events_url":"https://api.github.com/users/twostraws/events{/privacy}","received_events_url":"https://api.github.com/users/twostraws/received_events","type":"User","site_admin":false},"html_url":"https://github.com/twostraws/Sourceful","description":"A syntax highlighting source editor for iOS and macOS using UITextView and NSTextView.","fork":false,"url":"https://api.github.com/repos/twostraws/Sourceful","forks_url":"https://api.github.com/repos/twostraws/Sourceful/forks","keys_url":"https://api.github.com/repos/twostraws/Sourceful/keys{/key_id}","collaborators_url":"https://api.github.com/repos/twostraws/Sourceful/collaborators{/collaborator}","teams_url":"https://api.github.com/repos/twostraws/Sourceful/teams","hooks_url":"https://api.github.com/repos/twostraws/Sourceful/hooks","issue_events_url":"https://api.github.com/repos/twostraws/Sourceful/issues/events{/number}","events_url":"https://api.github.com/repos/twostraws/Sourceful/events","assignees_url":"https://api.github.com/repos/twostraws/Sourceful/assignees{/user}","branches_url":"https://api.github.com/repos/twostraws/Sourceful/branches{/branch}","tags_url":"https://api.github.com/repos/twostraws/Sourceful/tags","blobs_url":"https://api.github.com/repos/twostraws/Sourceful/git/blobs{/sha}","git_tags_url":"https://api.github.com/repos/twostraws/Sourceful/git/tags{/sha}","git_refs_url":"https://api.github.com/repos/twostraws/Sourceful/git/refs{/sha}","trees_url":"https://api.github.com/repos/twostraws/Sourceful/git/trees{/sha}","statuses_url":"https://api.github.com/repos/twostraws/Sourceful/statuses/{sha}","languages_url":"https://api.github.com/repos/twostraws/Sourceful/languages","stargazers_url":"https://api.github.com/repos/twostraws/Sourceful/stargazers","contributors_url":"https://api.github.com/repos/twostraws/Sourceful/contributors","subscribers_url":"https://api.github.com/repos/twostraws/Sourceful/subscribers","subscription_url":"https://api.github.com/repos/twostraws/Sourceful/subscription","commits_url":"https://api.github.com/repos/twostraws/Sourceful/commits{/sha}","git_commits_url":"https://api.github.com/repos/twostraws/Sourceful/git/commits{/sha}","comments_url":"https://api.github.com/repos/twostraws/Sourceful/comments{/number}","issue_comment_url":"https://api.github.com/repos/twostraws/Sourceful/issues/comments{/number}","contents_url":"https://api.github.com/repos/twostraws/Sourceful/contents/{+path}","compare_url":"https://api.github.com/repos/twostraws/Sourceful/compare/{base}...{head}","merges_url":"https://api.github.com/repos/twostraws/Sourceful/merges","archive_url":"https://api.github.com/repos/twostraws/Sourceful/{archive_format}{/ref}","downloads_url":"https://api.github.com/repos/twostraws/Sourceful/downloads","issues_url":"https://api.github.com/repos/twostraws/Sourceful/issues{/number}","pulls_url":"https://api.github.com/repos/twostraws/Sourceful/pulls{/number}","milestones_url":"https://api.github.com/repos/twostraws/Sourceful/milestones{/number}","notifications_url":"https://api.github.com/repos/twostraws/Sourceful/notifications{?since,all,participating}","labels_url":"https://api.github.com/repos/twostraws/Sourceful/labels{/name}","releases_url":"https://api.github.com/repos/twostraws/Sourceful/releases{/id}","deployments_url":"https://api.github.com/repos/twostraws/Sourceful/deployments","created_at":"2019-04-16T11:38:38Z","updated_at":"2019-12-13T18:14:36Z","pushed_at":"2019-09-24T09:01:08Z","git_url":"git://github.com/twostraws/Sourceful.git","ssh_url":"git@github.com:twostraws/Sourceful.git","clone_url":"https://github.com/twostraws/Sourceful.git","svn_url":"https://github.com/twostraws/Sourceful","homepage":"https://www.hackingwithswift.com","size":35,"stargazers_count":194,"watchers_count":194,"language":"Swift","has_issues":true,"has_projects":true,"has_downloads":true,"has_wiki":true,"has_pages":false,"forks_count":18,"mirror_url":null,"archived":false,"disabled":false,"open_issues_count":2,"license":{"key":"mit","name":"MIT License","spdx_id":"MIT","url":"https://api.github.com/licenses/mit","node_id":"MDc6TGljZW5zZTEz"},"topics":["appkit","ios","macos","swift","uikit","xcode"],"forks":18,"open_issues":2,"watchers":194,"default_branch":"master","permissions":{"admin":false,"push":false,"pull":true},"temp_clone_token":"","network_count":18,"subscribers_count":5}