{"id":22702040,"node_id":"MDEwOlJlcG9zaXRvcnkyMjcwMjA0MA==","name":"TableSchemer","full_name":"Weebly/TableSchemer","private":false,"owner":{"login":"Weebly","id":1890533,"node_id":"MDEyOk9yZ2FuaXphdGlvbjE4OTA1MzM=","avatar_url":"https://avatars1.githubusercontent.com/u/1890533?v=4","gravatar_id":"","url":"https://api.github.com/users/Weebly","html_url":"https://github.com/Weebly","followers_url":"https://api.github.com/users/Weebly/followers","following_url":"https://api.github.com/users/Weebly/following{/other_user}","gists_url":"https://api.github.com/users/Weebly/gists{/gist_id}","starred_url":"https://api.github.com/users/Weebly/starred{/owner}{/repo}","subscriptions_url":"https://api.github.com/users/Weebly/subscriptions","organizations_url":"https://api.github.com/users/Weebly/orgs","repos_url":"https://api.github.com/users/Weebly/repos","events_url":"https://api.github.com/users/Weebly/events{/privacy}","received_events_url":"https://api.github.com/users/Weebly/received_events","type":"Organization","site_admin":false},"html_url":"https://github.com/Weebly/TableSchemer","description":"Interactive static table views with ease","fork":false,"url":"https://api.github.com/repos/Weebly/TableSchemer","forks_url":"https://api.github.com/repos/Weebly/TableSchemer/forks","keys_url":"https://api.github.com/repos/Weebly/TableSchemer/keys{/key_id}","collaborators_url":"https://api.github.com/repos/Weebly/TableSchemer/collaborators{/collaborator}","teams_url":"https://api.github.com/repos/Weebly/TableSchemer/teams","hooks_url":"https://api.github.com/repos/Weebly/TableSchemer/hooks","issue_events_url":"https://api.github.com/repos/Weebly/TableSchemer/issues/events{/number}","events_url":"https://api.github.com/repos/Weebly/TableSchemer/events","assignees_url":"https://api.github.com/repos/Weebly/TableSchemer/assignees{/user}","branches_url":"https://api.github.com/repos/Weebly/TableSchemer/branches{/branch}","tags_url":"https://api.github.com/repos/Weebly/TableSchemer/tags","blobs_url":"https://api.github.com/repos/Weebly/TableSchemer/git/blobs{/sha}","git_tags_url":"https://api.github.com/repos/Weebly/TableSchemer/git/tags{/sha}","git_refs_url":"https://api.github.com/repos/Weebly/TableSchemer/git/refs{/sha}","trees_url":"https://api.github.com/repos/Weebly/TableSchemer/git/trees{/sha}","statuses_url":"https://api.github.com/repos/Weebly/TableSchemer/statuses/{sha}","languages_url":"https://api.github.com/repos/Weebly/TableSchemer/languages","stargazers_url":"https://api.github.com/repos/Weebly/TableSchemer/stargazers","contributors_url":"https://api.github.com/repos/Weebly/TableSchemer/contributors","subscribers_url":"https://api.github.com/repos/Weebly/TableSchemer/subscribers","subscription_url":"https://api.github.com/repos/Weebly/TableSchemer/subscription","commits_url":"https://api.github.com/repos/Weebly/TableSchemer/commits{/sha}","git_commits_url":"https://api.github.com/repos/Weebly/TableSchemer/git/commits{/sha}","comments_url":"https://api.github.com/repos/Weebly/TableSchemer/comments{/number}","issue_comment_url":"https://api.github.com/repos/Weebly/TableSchemer/issues/comments{/number}","contents_url":"https://api.github.com/repos/Weebly/TableSchemer/contents/{+path}","compare_url":"https://api.github.com/repos/Weebly/TableSchemer/compare/{base}...{head}","merges_url":"https://api.github.com/repos/Weebly/TableSchemer/merges","archive_url":"https://api.github.com/repos/Weebly/TableSchemer/{archive_format}{/ref}","downloads_url":"https://api.github.com/repos/Weebly/TableSchemer/downloads","issues_url":"https://api.github.com/repos/Weebly/TableSchemer/issues{/number}","pulls_url":"https://api.github.com/repos/Weebly/TableSchemer/pulls{/number}","milestones_url":"https://api.github.com/repos/Weebly/TableSchemer/milestones{/number}","notifications_url":"https://api.github.com/repos/Weebly/TableSchemer/notifications{?since,all,participating}","labels_url":"https://api.github.com/repos/Weebly/TableSchemer/labels{/name}","releases_url":"https://api.github.com/repos/Weebly/TableSchemer/releases{/id}","deployments_url":"https://api.github.com/repos/Weebly/TableSchemer/deployments","created_at":"2014-08-06T23:49:09Z","updated_at":"2019-06-15T23:40:38Z","pushed_at":"2019-07-08T19:00:11Z","git_url":"git://github.com/Weebly/TableSchemer.git","ssh_url":"git@github.com:Weebly/TableSchemer.git","clone_url":"https://github.com/Weebly/TableSchemer.git","svn_url":"https://github.com/Weebly/TableSchemer","homepage":null,"size":459,"stargazers_count":137,"watchers_count":137,"language":"Swift","has_issues":true,"has_projects":true,"has_downloads":true,"has_wiki":true,"has_pages":false,"forks_count":15,"mirror_url":null,"archived":false,"disabled":false,"open_issues_count":0,"license":{"key":"other","name":"Other","spdx_id":"NOASSERTION","url":null,"node_id":"MDc6TGljZW5zZTA="},"topics":[],"forks":15,"open_issues":0,"watchers":137,"default_branch":"master","permissions":{"admin":false,"push":false,"pull":true},"temp_clone_token":"","organization":{"login":"Weebly","id":1890533,"node_id":"MDEyOk9yZ2FuaXphdGlvbjE4OTA1MzM=","avatar_url":"https://avatars1.githubusercontent.com/u/1890533?v=4","gravatar_id":"","url":"https://api.github.com/users/Weebly","html_url":"https://github.com/Weebly","followers_url":"https://api.github.com/users/Weebly/followers","following_url":"https://api.github.com/users/Weebly/following{/other_user}","gists_url":"https://api.github.com/users/Weebly/gists{/gist_id}","starred_url":"https://api.github.com/users/Weebly/starred{/owner}{/repo}","subscriptions_url":"https://api.github.com/users/Weebly/subscriptions","organizations_url":"https://api.github.com/users/Weebly/orgs","repos_url":"https://api.github.com/users/Weebly/repos","events_url":"https://api.github.com/users/Weebly/events{/privacy}","received_events_url":"https://api.github.com/users/Weebly/received_events","type":"Organization","site_admin":false},"network_count":15,"subscribers_count":17}