{"id":54480848,"node_id":"MDEwOlJlcG9zaXRvcnk1NDQ4MDg0OA==","name":"YPWebView","full_name":"dadage456/YPWebView","private":false,"owner":{"login":"dadage456","id":3982037,"node_id":"MDQ6VXNlcjM5ODIwMzc=","avatar_url":"https://avatars3.githubusercontent.com/u/3982037?v=4","gravatar_id":"","url":"https://api.github.com/users/dadage456","html_url":"https://github.com/dadage456","followers_url":"https://api.github.com/users/dadage456/followers","following_url":"https://api.github.com/users/dadage456/following{/other_user}","gists_url":"https://api.github.com/users/dadage456/gists{/gist_id}","starred_url":"https://api.github.com/users/dadage456/starred{/owner}{/repo}","subscriptions_url":"https://api.github.com/users/dadage456/subscriptions","organizations_url":"https://api.github.com/users/dadage456/orgs","repos_url":"https://api.github.com/users/dadage456/repos","events_url":"https://api.github.com/users/dadage456/events{/privacy}","received_events_url":"https://api.github.com/users/dadage456/received_events","type":"User","site_admin":false},"html_url":"https://github.com/dadage456/YPWebView","description":"混合UIWebView和WKWebView,根据系统自动选择控件。。。","fork":false,"url":"https://api.github.com/repos/dadage456/YPWebView","forks_url":"https://api.github.com/repos/dadage456/YPWebView/forks","keys_url":"https://api.github.com/repos/dadage456/YPWebView/keys{/key_id}","collaborators_url":"https://api.github.com/repos/dadage456/YPWebView/collaborators{/collaborator}","teams_url":"https://api.github.com/repos/dadage456/YPWebView/teams","hooks_url":"https://api.github.com/repos/dadage456/YPWebView/hooks","issue_events_url":"https://api.github.com/repos/dadage456/YPWebView/issues/events{/number}","events_url":"https://api.github.com/repos/dadage456/YPWebView/events","assignees_url":"https://api.github.com/repos/dadage456/YPWebView/assignees{/user}","branches_url":"https://api.github.com/repos/dadage456/YPWebView/branches{/branch}","tags_url":"https://api.github.com/repos/dadage456/YPWebView/tags","blobs_url":"https://api.github.com/repos/dadage456/YPWebView/git/blobs{/sha}","git_tags_url":"https://api.github.com/repos/dadage456/YPWebView/git/tags{/sha}","git_refs_url":"https://api.github.com/repos/dadage456/YPWebView/git/refs{/sha}","trees_url":"https://api.github.com/repos/dadage456/YPWebView/git/trees{/sha}","statuses_url":"https://api.github.com/repos/dadage456/YPWebView/statuses/{sha}","languages_url":"https://api.github.com/repos/dadage456/YPWebView/languages","stargazers_url":"https://api.github.com/repos/dadage456/YPWebView/stargazers","contributors_url":"https://api.github.com/repos/dadage456/YPWebView/contributors","subscribers_url":"https://api.github.com/repos/dadage456/YPWebView/subscribers","subscription_url":"https://api.github.com/repos/dadage456/YPWebView/subscription","commits_url":"https://api.github.com/repos/dadage456/YPWebView/commits{/sha}","git_commits_url":"https://api.github.com/repos/dadage456/YPWebView/git/commits{/sha}","comments_url":"https://api.github.com/repos/dadage456/YPWebView/comments{/number}","issue_comment_url":"https://api.github.com/repos/dadage456/YPWebView/issues/comments{/number}","contents_url":"https://api.github.com/repos/dadage456/YPWebView/contents/{+path}","compare_url":"https://api.github.com/repos/dadage456/YPWebView/compare/{base}...{head}","merges_url":"https://api.github.com/repos/dadage456/YPWebView/merges","archive_url":"https://api.github.com/repos/dadage456/YPWebView/{archive_format}{/ref}","downloads_url":"https://api.github.com/repos/dadage456/YPWebView/downloads","issues_url":"https://api.github.com/repos/dadage456/YPWebView/issues{/number}","pulls_url":"https://api.github.com/repos/dadage456/YPWebView/pulls{/number}","milestones_url":"https://api.github.com/repos/dadage456/YPWebView/milestones{/number}","notifications_url":"https://api.github.com/repos/dadage456/YPWebView/notifications{?since,all,participating}","labels_url":"https://api.github.com/repos/dadage456/YPWebView/labels{/name}","releases_url":"https://api.github.com/repos/dadage456/YPWebView/releases{/id}","deployments_url":"https://api.github.com/repos/dadage456/YPWebView/deployments","created_at":"2016-03-22T14:18:04Z","updated_at":"2018-05-12T14:14:48Z","pushed_at":"2016-08-22T06:36:56Z","git_url":"git://github.com/dadage456/YPWebView.git","ssh_url":"git@github.com:dadage456/YPWebView.git","clone_url":"https://github.com/dadage456/YPWebView.git","svn_url":"https://github.com/dadage456/YPWebView","homepage":null,"size":122,"stargazers_count":21,"watchers_count":21,"language":"Objective-C","has_issues":true,"has_projects":true,"has_downloads":true,"has_wiki":true,"has_pages":false,"forks_count":3,"mirror_url":null,"archived":false,"disabled":false,"open_issues_count":1,"license":{"key":"mit","name":"MIT License","spdx_id":"MIT","url":"https://api.github.com/licenses/mit","node_id":"MDc6TGljZW5zZTEz"},"topics":[],"forks":3,"open_issues":1,"watchers":21,"default_branch":"master","permissions":{"admin":false,"push":false,"pull":true},"temp_clone_token":"","network_count":3,"subscribers_count":1}