{"id":42397191,"node_id":"MDEwOlJlcG9zaXRvcnk0MjM5NzE5MQ==","name":"ZProgress","full_name":"zhuayi/ZProgress","private":false,"owner":{"login":"zhuayi","id":1287348,"node_id":"MDQ6VXNlcjEyODczNDg=","avatar_url":"https://avatars1.githubusercontent.com/u/1287348?v=4","gravatar_id":"","url":"https://api.github.com/users/zhuayi","html_url":"https://github.com/zhuayi","followers_url":"https://api.github.com/users/zhuayi/followers","following_url":"https://api.github.com/users/zhuayi/following{/other_user}","gists_url":"https://api.github.com/users/zhuayi/gists{/gist_id}","starred_url":"https://api.github.com/users/zhuayi/starred{/owner}{/repo}","subscriptions_url":"https://api.github.com/users/zhuayi/subscriptions","organizations_url":"https://api.github.com/users/zhuayi/orgs","repos_url":"https://api.github.com/users/zhuayi/repos","events_url":"https://api.github.com/users/zhuayi/events{/privacy}","received_events_url":"https://api.github.com/users/zhuayi/received_events","type":"User","site_admin":false},"html_url":"https://github.com/zhuayi/ZProgress","description":"ZProgress是一款自定义非常方便的进度条控件, 支持横向,纵向,圆形等展示方式,简单, 高效, 样式丰富.","fork":false,"url":"https://api.github.com/repos/zhuayi/ZProgress","forks_url":"https://api.github.com/repos/zhuayi/ZProgress/forks","keys_url":"https://api.github.com/repos/zhuayi/ZProgress/keys{/key_id}","collaborators_url":"https://api.github.com/repos/zhuayi/ZProgress/collaborators{/collaborator}","teams_url":"https://api.github.com/repos/zhuayi/ZProgress/teams","hooks_url":"https://api.github.com/repos/zhuayi/ZProgress/hooks","issue_events_url":"https://api.github.com/repos/zhuayi/ZProgress/issues/events{/number}","events_url":"https://api.github.com/repos/zhuayi/ZProgress/events","assignees_url":"https://api.github.com/repos/zhuayi/ZProgress/assignees{/user}","branches_url":"https://api.github.com/repos/zhuayi/ZProgress/branches{/branch}","tags_url":"https://api.github.com/repos/zhuayi/ZProgress/tags","blobs_url":"https://api.github.com/repos/zhuayi/ZProgress/git/blobs{/sha}","git_tags_url":"https://api.github.com/repos/zhuayi/ZProgress/git/tags{/sha}","git_refs_url":"https://api.github.com/repos/zhuayi/ZProgress/git/refs{/sha}","trees_url":"https://api.github.com/repos/zhuayi/ZProgress/git/trees{/sha}","statuses_url":"https://api.github.com/repos/zhuayi/ZProgress/statuses/{sha}","languages_url":"https://api.github.com/repos/zhuayi/ZProgress/languages","stargazers_url":"https://api.github.com/repos/zhuayi/ZProgress/stargazers","contributors_url":"https://api.github.com/repos/zhuayi/ZProgress/contributors","subscribers_url":"https://api.github.com/repos/zhuayi/ZProgress/subscribers","subscription_url":"https://api.github.com/repos/zhuayi/ZProgress/subscription","commits_url":"https://api.github.com/repos/zhuayi/ZProgress/commits{/sha}","git_commits_url":"https://api.github.com/repos/zhuayi/ZProgress/git/commits{/sha}","comments_url":"https://api.github.com/repos/zhuayi/ZProgress/comments{/number}","issue_comment_url":"https://api.github.com/repos/zhuayi/ZProgress/issues/comments{/number}","contents_url":"https://api.github.com/repos/zhuayi/ZProgress/contents/{+path}","compare_url":"https://api.github.com/repos/zhuayi/ZProgress/compare/{base}...{head}","merges_url":"https://api.github.com/repos/zhuayi/ZProgress/merges","archive_url":"https://api.github.com/repos/zhuayi/ZProgress/{archive_format}{/ref}","downloads_url":"https://api.github.com/repos/zhuayi/ZProgress/downloads","issues_url":"https://api.github.com/repos/zhuayi/ZProgress/issues{/number}","pulls_url":"https://api.github.com/repos/zhuayi/ZProgress/pulls{/number}","milestones_url":"https://api.github.com/repos/zhuayi/ZProgress/milestones{/number}","notifications_url":"https://api.github.com/repos/zhuayi/ZProgress/notifications{?since,all,participating}","labels_url":"https://api.github.com/repos/zhuayi/ZProgress/labels{/name}","releases_url":"https://api.github.com/repos/zhuayi/ZProgress/releases{/id}","deployments_url":"https://api.github.com/repos/zhuayi/ZProgress/deployments","created_at":"2015-09-13T13:39:57Z","updated_at":"2017-10-22T14:44:15Z","pushed_at":"2017-03-01T11:04:00Z","git_url":"git://github.com/zhuayi/ZProgress.git","ssh_url":"git@github.com:zhuayi/ZProgress.git","clone_url":"https://github.com/zhuayi/ZProgress.git","svn_url":"https://github.com/zhuayi/ZProgress","homepage":"","size":391,"stargazers_count":4,"watchers_count":4,"language":"Objective-C","has_issues":true,"has_projects":true,"has_downloads":true,"has_wiki":true,"has_pages":false,"forks_count":3,"mirror_url":null,"archived":false,"disabled":false,"open_issues_count":0,"license":{"key":"mit","name":"MIT License","spdx_id":"MIT","url":"https://api.github.com/licenses/mit","node_id":"MDc6TGljZW5zZTEz"},"topics":[],"forks":3,"open_issues":0,"watchers":4,"default_branch":"master","permissions":{"admin":false,"push":false,"pull":true},"temp_clone_token":"","network_count":3,"subscribers_count":1}